<?xml version="1.0" encoding="UTF-8"?>
<openerp>
    <data>
        <!-- Vista tipo tree del modelo materiales.listaprecios -->
        <record model="ir.ui.view" id="materiales_listaprecios_tree">
            <field name="name">materiales.listaprecios.tree</field>
            <field name="model">materiales.listaprecios</field>
            <field name="type">tree</field>
            <field name="arch" type="xml">
                <tree string="Lista de Precios">
                    <field name="fecha"/>
                    <field name="proveedor_id"/>
                    <field name="aplicado"/>
                </tree>
            </field>
        </record>

        <!-- Vista tipo form del modelo materiales.listaprecios -->
        <record model="ir.ui.view" id="materiales_listaprecios_form">
            <field name="name">materiales.listaprecios.form</field>
            <field name="model">materiales.listaprecios</field>
            <field name="type">form</field>
            <field name="arch" type="xml">
                <form string="Lista de Precios">
                    <header>
                        <button name="actualizar_precio" type="object" string="Actualizar Precio" class="oe_highlight" status="!aplicado"/>
                    </header>
                    <sheet>
                        <group>
                            <field name="fecha" readonly="1"/>
                            <field name="proveedor_id"/>
                            <field name="aplicado"/>
                        </group>
                        <notebook>
                            <page string="Detalles de Lista de Precios">
                                <field name="line_ids" widget="one2many_list">
                                    <tree editable="bottom">
                                        <field name="producto_id"/>
                                        <field name="clave"/>
                                        <field name="nombre"/>
                                        <field name="precio_actual"/>
                                        <field name="nuevo_precio"/>
                                    </tree>
                                </field>
                            </page>
                        </notebook>
                    </sheet>
                </form>
            </field>
        </record>

        <!-- Vista de búsqueda del modelo materiales.listaprecios -->
        <record model="ir.ui.view" id="materiales_listaprecios_search">
            <field name="name">materiales.listaprecios.search</field>
            <field name="model">materiales.listaprecios</field>
            <field name="arch" type="xml">
                <search>
                    <field name="fecha"/>
                    <field name="proveedor_id"/>
                    <field name="producto_id"/>
                    <field name="aplicado"/>
                </search>
            </field>
        </record>

        <!-- Acción para el modelo de lista de precios -->
        <record id="materiales_listaprecios_action" model="ir.actions.act_window">
            <field name="name">Listas de Precios</field>
            <field name="res_model">materiales.listaprecios</field>
            <field name="view_mode">tree,form</field>
            <field name="search_view_id" ref="materiales_listaprecios_search"/>
        </record>
    </data>
</openerp>
